cuddly_dicts/__about__.py
cuddly_dicts/__init__.py
cuddly_dicts/__main__.py
cuddly_dicts-3.0.2.dist-info/METADATA
cuddly_dicts-3.0.2.dist-info/WHEEL
cuddly_dicts-3.0.2.dist-info/licenses/LICENSE-MIT.txt
cuddly_dicts-3.0.2.dist-info/licenses/LICENSE-WTFPL.txt
cuddly_dicts-3.0.2.dist-info/RECORD
