Metadata-Version: 2.4
Name: cuddly-dicts
Version: 3.0.2
Project-URL: Documentation, https://github.com/iamawatermelo/cuddly-dicts#readme
Project-URL: Issues, https://github.com/iamawatermelo/cuddly-dicts/issues
Project-URL: Source, https://github.com/iamawatermelo/cuddly-dicts
Author-email: Sarah C <pypi-maintainer@srh.dog>
License-Expression: MIT
License-File: LICENSE-MIT.txt
License-File: LICENSE-WTFPL.txt
Classifier: Development Status :: 4 - Beta
Classifier: Programming Language :: Python
Classifier: Programming Language :: Python :: 3.12
Classifier: Programming Language :: Python :: Implementation :: CPython
Requires-Python: >=3.12
Requires-Dist: kdl-py~=1.2.0
